qtoggleserver/modbus/__init__.py
qtoggleserver/modbus/base.py
qtoggleserver/modbus/client.py
qtoggleserver/modbus/constants.py
qtoggleserver/modbus/ports.py
qtoggleserver/modbus/server.py
qtoggleserver/modbus/passive/__init__.py
qtoggleserver/modbus/passive/base.py
qtoggleserver/modbus/passive/serial.py
qtoggleserver/modbus/passive/tcpdump.py
qtoggleserver_modbus-1.3.1.dist-info/licenses/LICENSE.txt
qtoggleserver_modbus-1.3.1.dist-info/METADATA
qtoggleserver_modbus-1.3.1.dist-info/WHEEL
qtoggleserver_modbus-1.3.1.dist-info/top_level.txt
qtoggleserver_modbus-1.3.1.dist-info/RECORD
