Metadata-Version: 2.4
Name: qtoggleserver-modbus
Version: 1.3.1
Summary: Modbus client/server for qToggleServer
Author-email: Calin Crisan <ccrisan@gmail.com>
License: Apache 2.0
Requires-Python: >=3.11
License-File: LICENSE.txt
Requires-Dist: pymodbus<3.7,>=3.6
Requires-Dist: pyserial<4,>=3
Dynamic: license-file
